webstompy/__init__.py
webstompy/connection.py
webstompy/exception.py
webstompy/frame.py
webstompy/listener.py
webstompy/logging.py
webstompy/receiver.py
webstompy/tests/test_version.py
webstompy/transporter/__init__.py
webstompy/transporter/transporter.py
webstompy/version.py
webstompy-0.1.5.dist-info/LICENSE
webstompy-0.1.5.dist-info/METADATA
webstompy-0.1.5.dist-info/WHEEL
webstompy-0.1.5.dist-info/RECORD
