Metadata-Version: 2.3
Name: webstompy
Version: 0.1.5
Summary: A simple Python STOMP implementation with WebSocket support
License: MIT
Author: Point 8 GmbH
Author-email: kontakt@point-8.de
Requires-Python: >=3.8
Classifier: License :: OSI Approved :: MIT License
Classifier: Programming Language :: Python :: 3
Classifier: Programming Language :: Python :: 3.8
Classifier: Programming Language :: Python :: 3.9
Classifier: Programming Language :: Python :: 3.10
Classifier: Programming Language :: Python :: 3.11
Classifier: Programming Language :: Python :: 3.12
Classifier: Programming Language :: Python :: 3.13
Requires-Dist: websocket-client (>=1.8.0)
